jaxnnls/__init__.py
jaxnnls/diff_qp.py
jaxnnls/pdip.py
jaxnnls/pdip_relaxed.py
jaxnnls/tests/__init__.py
jaxnnls/tests/test_nnls.py
jaxnnls-1.0.1.dist-info/licenses/LICENSE
jaxnnls-1.0.1.dist-info/WHEEL
jaxnnls-1.0.1.dist-info/METADATA
jaxnnls-1.0.1.dist-info/RECORD
