Metadata-Version: 2.4
Name: jaxnnls
Version: 1.0.1
Summary: The jaxnnls package provides functions to solve non-negative
Author-email: Coleman Krawczyk <coleman.krawczyk@port.ac.uk>
License-Expression: MIT
License-File: LICENSE
Requires-Dist: jax >=0.4.0
Requires-Dist: jaxlib >=0.4.0
Requires-Dist: myst-nb >=0.15.0 ; extra == "doc"
Requires-Dist: sphinx >=4.5.0 ; extra == "doc"
Requires-Dist: sphinx_rtd_theme >=1.0.0 ; extra == "doc"
Requires-Dist: coverage[toml] >=6.3.2 ; extra == "test"
Requires-Dist: Flake8-pyproject >=1.2.3 ; extra == "test"
Project-URL: Documentation, https://ckrawczyk.github.io/JaxNNLS/
Project-URL: Source, https://github.com/CKrawczyk/JaxNNLS
Provides-Extra: doc
Provides-Extra: test
